LICENSE
MANIFEST.in
README.rst
VERSION
requirements.txt
setup.cfg
setup.py
doc/architecture-optel.rst
doc/changelog.rst
doc/cluster.rst
doc/conf.py
doc/devel-job.rst
doc/devel.rst
doc/index.rst
doc/install.rst
doc/introduction.rst
doc/refinery.rst
doc/tdd.rst
doc/usage.rst
optel/__init__.py
optel.datalake.egg-info/PKG-INFO
optel.datalake.egg-info/SOURCES.txt
optel.datalake.egg-info/dependency_links.txt
optel.datalake.egg-info/entry_points.txt
optel.datalake.egg-info/requires.txt
optel.datalake.egg-info/top_level.txt
optel/datalake/__init__.py
optel/datalake/__main__.py
optel/datalake/big_query.py
optel/datalake/descriptive_stats.py
optel/datalake/ingest.py
optel/datalake/sanity_checks.py
optel/datalake/transform.py
optel/datalake/utils.py
optel/datalake/bigquery/__init__.py
optel/datalake/bigquery/client.py
optel/datalake/config/__init__.py
optel/datalake/config/db.py
optel/datalake/config/elastic.py
optel/datalake/config/sparksession.py
optel/datalake/models/__init__.py
optel/datalake/models/job.py
optel/datalake/models/pipeline.py
optel/datalake/models/schemas.py
optel/datalake/models/tables.py
requirements/dev.txt
requirements/doc.txt
requirements/prod.txt
tests/__init__.py
tests/cloud_test.py
tests/conftest.py
tests/test_big_query.py
tests/test_bigquery.py
tests/test_cloud_test_ci.py
tests/test_config.py
tests/test_descriptive_stats.py
tests/test_ingest.py
tests/test_sanity_checks.py
tests/test_transform.py
tests/test_utils.py
tests/bigquery/__init__.py
tests/bigquery/test_client.py
tests/models/__init__.py
tests/models/test_job.py
tests/models/test_pipeline.py
tests/models/test_schema.py
tests/models/test_tables.py