Metadata-Version: 1.1
Name: optel.datalake
Version: 2.2.1
Summary: Common tools used in the data refinery
Home-page: https://www.optelgroup.com/
Author: Optel Business Technologies Team
Author-email: btechsupport@optelgroup.com
License: LGPL
Platform: UNKNOWN
Classifier: Development Status :: 4 - Beta
Classifier: Intended Audience :: Developers
Classifier: Programming Language :: Python :: 3.6
Classifier: Topic :: Utilities
